envex/__init__.py
envex/dot_env.py
envex/env_crypto.py
envex/env_hvac.py
envex/env_wrapper.py
envex/scripts/__init__.py
envex/scripts/env2hvac.py
envex/scripts/envcrypt.py
envex/scripts/envsecrets.py
envex/scripts/seal.py
envex/scripts/example/example.env
envex/scripts/example/example.sh
envex/scripts/example/template.env
envex/scripts/lib/__init__.py
envex/scripts/lib/decr_action.py
envex/scripts/lib/log.py
envex-4.2.0.dist-info/entry_points.txt
envex-4.2.0.dist-info/licenses/LICENSE.md
envex-4.2.0.dist-info/WHEEL
envex-4.2.0.dist-info/METADATA
envex-4.2.0.dist-info/RECORD
