Metadata-Version: 2.4
Name: envex
Version: 4.2.0
Summary: Environment interface with (optionally encrypted) .env with hashicorp vault support
Author-email: David Nugent <davidn@uniquode.io>
Requires-Python: >=3.11
Classifier: Programming Language :: Python :: 3
Classifier: Programming Language :: Python :: 3.11
Classifier: Programming Language :: Python :: 3.12
Classifier: Programming Language :: Python :: 3.13
Classifier: Programming Language :: Python :: 3 :: Only
License-File: LICENSE.md
Requires-Dist: pycryptodome>=3.21.0
Project-URL: homepage, https://github.com/deeprave/envex
Project-URL: repository, https://github.com/deeprave/envex
